cluster_experiments/__init__.py
cluster_experiments/cupac.py
cluster_experiments/experiment_analysis.py
cluster_experiments/perturbator.py
cluster_experiments/power_analysis.py
cluster_experiments/power_config.py
cluster_experiments/random_splitter.py
cluster_experiments/relative_lift_transformer.py
cluster_experiments/synthetic_control_utils.py
cluster_experiments/utils.py
cluster_experiments/washover.py
cluster_experiments/inference/__init__.py
cluster_experiments/inference/analysis_plan.py
cluster_experiments/inference/analysis_plan_config.py
cluster_experiments/inference/analysis_results.py
cluster_experiments/inference/dimension.py
cluster_experiments/inference/hypothesis_test.py
cluster_experiments/inference/metric.py
cluster_experiments/inference/variant.py
cluster_experiments-0.29.0.dist-info/licenses/LICENSE
tests/__init__.py
tests/test_docs.py
tests/test_non_clustered.py
tests/test_utils.py
tests/utils.py
tests/analysis/__init__.py
tests/analysis/conftest.py
tests/analysis/test_analysis.py
tests/analysis/test_delta_e2e.py
tests/analysis/test_delta_method.py
tests/analysis/test_formula.py
tests/analysis/test_hypothesis.py
tests/analysis/test_lift_transformer.py
tests/analysis/test_ols_analysis.py
tests/analysis/test_synthetic_analysis.py
tests/cupac/__init__.py
tests/cupac/conftest.py
tests/cupac/test_aggregator.py
tests/cupac/test_cupac_handler.py
tests/inference/__init__.py
tests/inference/conftest.py
tests/inference/test_analysis_plan.py
tests/inference/test_analysis_plan_config.py
tests/inference/test_analysis_results.py
tests/inference/test_delta_method.py
tests/inference/test_dimension.py
tests/inference/test_hypothesis_test.py
tests/inference/test_metric.py
tests/inference/test_variant.py
tests/perturbator/__init__.py
tests/perturbator/conftest.py
tests/perturbator/test_perturbator.py
tests/power_analysis/__init__.py
tests/power_analysis/conftest.py
tests/power_analysis/test_cupac_power.py
tests/power_analysis/test_multivariate.py
tests/power_analysis/test_normal_power_analysis.py
cluster_experiments-0.29.0.dist-info/METADATA
cluster_experiments-0.29.0.dist-info/WHEEL
cluster_experiments-0.29.0.dist-info/top_level.txt
cluster_experiments-0.29.0.dist-info/RECORD
