Metadata-Version: 2.4
Name: cluster-experiments
Version: 0.29.0
Classifier: Development Status :: 4 - Beta
Classifier: Intended Audience :: Developers
Classifier: Programming Language :: Python
Classifier: Programming Language :: Python :: 3.9
Classifier: Programming Language :: Python :: 3.10
Classifier: Programming Language :: Python :: 3.11
Classifier: Programming Language :: Python :: 3.12
Classifier: Programming Language :: Python :: 3.13
Classifier: Programming Language :: Python :: 3 :: Only
Classifier: Operating System :: OS Independent
Classifier: License :: OSI Approved :: MIT License
Requires-Python: <3.13,>=3.9
License-File: LICENSE
Requires-Dist: pip>=22.2.2
Requires-Dist: statsmodels>=0.13.2
Requires-Dist: pandas>=1.2.0
Requires-Dist: scikit-learn>=1.0.0
Requires-Dist: tqdm>=4.0.0
Requires-Dist: numpy>=1.20.0
Provides-Extra: dev
Requires-Dist: pytest<9.0.0,>=5.4.3; extra == "dev"
Requires-Dist: black<25.0.0,>=22.12.0; extra == "dev"
Requires-Dist: ruff<1.0.0,>=0.7.4; extra == "dev"
Requires-Dist: mktestdocs<1.0.0,>=0.2.2; extra == "dev"
Requires-Dist: pytest-cov<7.0.0,>=2.10.1; extra == "dev"
Requires-Dist: pytest-sugar<2.0.0,>=0.9.4; extra == "dev"
Requires-Dist: pytest-slow-last<1.0.0,>=0.1.3; extra == "dev"
Requires-Dist: coverage<8.0.0,>=7.6.7; extra == "dev"
Requires-Dist: pytest-reportlog<1.0.0,>=0.4.0; extra == "dev"
Requires-Dist: pytest-duration-insights<1.0.0,>=0.1.2; extra == "dev"
Requires-Dist: pytest-clarity<2.0.0,>=1.0.1; extra == "dev"
Requires-Dist: pytest-xdist<4.0.0,>=3.6.1; extra == "dev"
Requires-Dist: pre-commit<5.0.0,>=2.6.0; extra == "dev"
Requires-Dist: ipykernel<7.0.0,>=6.15.1; extra == "dev"
Requires-Dist: twine<6.0.0,>=5.1.1; extra == "dev"
Requires-Dist: build<2.0.0.0,>=1.2.2.post1; extra == "dev"
Requires-Dist: tox<5.0.0,>=4.23.2; extra == "dev"
Requires-Dist: mkdocs<2.0.0,>=1.4.0; extra == "dev"
Requires-Dist: mkdocs-material<10.0.0,>=8.5.0; extra == "dev"
Requires-Dist: mkdocstrings[python]<1.0.0,>=0.25.0; extra == "dev"
Requires-Dist: jinja2<4.0.0,>=3.1.0; extra == "dev"
Requires-Dist: mkdocs-jupyter<1.0.0,>=0.22.0; extra == "dev"
Requires-Dist: matplotlib<4.0.0,>=3.4.3; extra == "dev"
Requires-Dist: plotnine<1.0.0,>=0.8.0; extra == "dev"
Provides-Extra: test
Requires-Dist: pytest<9.0.0,>=5.4.3; extra == "test"
Requires-Dist: black<25.0.0,>=22.12.0; extra == "test"
Requires-Dist: ruff<1.0.0,>=0.7.4; extra == "test"
Requires-Dist: mktestdocs<1.0.0,>=0.2.2; extra == "test"
Requires-Dist: pytest-cov<7.0.0,>=2.10.1; extra == "test"
Requires-Dist: pytest-sugar<2.0.0,>=0.9.4; extra == "test"
Requires-Dist: pytest-slow-last<1.0.0,>=0.1.3; extra == "test"
Requires-Dist: coverage<8.0.0,>=7.6.7; extra == "test"
Requires-Dist: pytest-reportlog<1.0.0,>=0.4.0; extra == "test"
Requires-Dist: pytest-duration-insights<1.0.0,>=0.1.2; extra == "test"
Requires-Dist: pytest-clarity<2.0.0,>=1.0.1; extra == "test"
Requires-Dist: pytest-xdist<4.0.0,>=3.6.1; extra == "test"
Provides-Extra: docs
Requires-Dist: mkdocs<2.0.0,>=1.4.0; extra == "docs"
Requires-Dist: mkdocs-material<10.0.0,>=8.5.0; extra == "docs"
Requires-Dist: mkdocstrings<1.0.0,>=0.18.0; extra == "docs"
Requires-Dist: jinja2<4.0.0,>=3.1.0; extra == "docs"
Requires-Dist: mkdocs-jupyter<1.0.0,>=0.22.0; extra == "docs"
Requires-Dist: plotnine<1.0.0,>=0.8.0; extra == "docs"
Requires-Dist: matplotlib<4.0.0,>=3.4.3; extra == "docs"
Dynamic: license-file
